markymark.py
setup.py
markymark.egg-info/PKG-INFO
markymark.egg-info/SOURCES.txt
markymark.egg-info/dependency_links.txt
markymark.egg-info/entry_points.txt
markymark.egg-info/top_level.txt