Metadata-Version: 1.0
Name: markymark
Version: 0.3
Summary: Make your console text funky!
Home-page: http://github.com/jbowes/markymark
Author: James Bowes
Author-email: jbowes@dangerouslyinc.com
License: MIT
Keywords: cli,console,text,color,ANSI
Platform: any
Classifier: Development Status :: 4 - Beta
Classifier: Environment :: Console
Classifier: Intended Audience :: Developers
Classifier: Intended Audience :: System Administrators
Classifier: Intended Audience :: Other Audience
Classifier: License :: OSI Approved :: MIT License
Classifier: Topic :: Software Development :: Libraries
Classifier: Topic :: Software Development :: User Interfaces
Classifier: Topic :: Text Processing :: Markup
Classifier: Topic :: Utilities
